LICENSE
README.md
setup.py
gurux_dlms_agent/DlmsAgent.py
gurux_dlms_agent/GXDLMSReader.py
gurux_dlms_agent/GXDLMSSecureClient2.py
gurux_dlms_agent/GXSettings.py
gurux_dlms_agent/__init__.py
gurux_dlms_agent.egg-info/PKG-INFO
gurux_dlms_agent.egg-info/SOURCES.txt
gurux_dlms_agent.egg-info/dependency_links.txt
gurux_dlms_agent.egg-info/top_level.txt